LICENSE
MANIFEST.in
README.txt
setup.py
flask_cfg/__init__.py
flask_cfg/core.py
flask_cfg.egg-info/PKG-INFO
flask_cfg.egg-info/SOURCES.txt
flask_cfg.egg-info/dependency_links.txt
flask_cfg.egg-info/top_level.txt
flask_cfg/tests/__init__.py
flask_cfg/tests/core_test.py