Metadata-Version: 2.1
Name: flask-cfg
Version: 0.0.6
Summary: A little package for loading Flask configurations from YAML files.
Home-page: https://github.com/ikumen/flask-cfg
Author: Thong Nguyen
Author-email: thong@gnoht.com
License: UNKNOWN
Platform: UNKNOWN
Classifier: Programming Language :: Python :: 2
Classifier: License :: OSI Approved :: MIT License
Classifier: Operating System :: OS Independent
